odoo/addons/mail_attach_existing_attachment_account/README.rst
odoo/addons/mail_attach_existing_attachment_account/__init__.py
odoo/addons/mail_attach_existing_attachment_account/__manifest__.py
odoo/addons/mail_attach_existing_attachment_account/i18n/it.po
odoo/addons/mail_attach_existing_attachment_account/i18n/mail_attach_existing_attachment_account.pot
odoo/addons/mail_attach_existing_attachment_account/readme/CONTRIBUTORS.md
odoo/addons/mail_attach_existing_attachment_account/readme/DESCRIPTION.md
odoo/addons/mail_attach_existing_attachment_account/static/description/icon.png
odoo/addons/mail_attach_existing_attachment_account/static/description/index.html
odoo/addons/mail_attach_existing_attachment_account/tests/__init__.py
odoo/addons/mail_attach_existing_attachment_account/tests/test_mail_attach_existing_attachment_account.py
odoo/addons/mail_attach_existing_attachment_account/wizard/__init__.py
odoo/addons/mail_attach_existing_attachment_account/wizard/account_move_send.py
odoo/addons/mail_attach_existing_attachment_account/wizard/account_move_send_view.xml
odoo_addon_mail_attach_existing_attachment_account-17.0.1.0.0.2.dist-info/METADATA
odoo_addon_mail_attach_existing_attachment_account-17.0.1.0.0.2.dist-info/WHEEL
odoo_addon_mail_attach_existing_attachment_account-17.0.1.0.0.2.dist-info/top_level.txt
odoo_addon_mail_attach_existing_attachment_account-17.0.1.0.0.2.dist-info/RECORD
